div_dialogs
