Metadata-Version: 1.0
Name: DivDialogs
Version: 0.1a1.dev-r610
Summary: A few dialogs (modal or not) to improve the UI usability of TurboGear apps
Home-page: UNKNOWN
Author: Claudio Martinez
Author-email: claudio.s.martinez@gmail.com
License: MIT
Keywords: turbogears.widgets
Platform: UNKNOWN
Classifier: Development Status :: 3 - Alpha
Classifier: Operating System :: OS Independent
Classifier: Programming Language :: Python
Classifier: Topic :: Software Development :: Libraries :: Python Modules
Classifier: Framework :: TurboGears
Classifier: Framework :: TurboGears :: Widgets
